csvshark/__init__.py
csvshark/csvshark.py
csvshark-1.1.dist-info/METADATA
csvshark-1.1.dist-info/WHEEL
csvshark-1.1.dist-info/top_level.txt
csvshark-1.1.dist-info/RECORD
